easyLDA/__init__.py
easyLDA/base.py
easyLDA/stop.py
easyLDA-0.2.8.6.dist-info/DESCRIPTION.rst
easyLDA-0.2.8.6.dist-info/METADATA
easyLDA-0.2.8.6.dist-info/RECORD
easyLDA-0.2.8.6.dist-info/WHEEL
easyLDA-0.2.8.6.dist-info/entry_points.txt
easyLDA-0.2.8.6.dist-info/metadata.json
easyLDA-0.2.8.6.dist-info/top_level.txt
